RsCmwWcdmaMeas/RsCmwWcdmaMeas.py
RsCmwWcdmaMeas/__init__.py
RsCmwWcdmaMeas/enums.py
RsCmwWcdmaMeas/repcap.py
RsCmwWcdmaMeas/CustomFiles/__init__.py
RsCmwWcdmaMeas/CustomFiles/events.py
RsCmwWcdmaMeas/CustomFiles/reliability.py
RsCmwWcdmaMeas/CustomFiles/utilities.py
RsCmwWcdmaMeas/Implementations/Configure.py
RsCmwWcdmaMeas/Implementations/MultiEval.py
RsCmwWcdmaMeas/Implementations/OlpControl.py
RsCmwWcdmaMeas/Implementations/OoSync.py
RsCmwWcdmaMeas/Implementations/Prach.py
RsCmwWcdmaMeas/Implementations/Route.py
RsCmwWcdmaMeas/Implementations/Tpc.py
RsCmwWcdmaMeas/Implementations/Trigger.py
RsCmwWcdmaMeas/Implementations/__init__.py
RsCmwWcdmaMeas/Implementations/Configure_/Carrier.py
RsCmwWcdmaMeas/Implementations/Configure_/Cell.py
RsCmwWcdmaMeas/Implementations/Configure_/MultiEval.py
RsCmwWcdmaMeas/Implementations/Configure_/OlpControl.py
RsCmwWcdmaMeas/Implementations/Configure_/OoSync.py
RsCmwWcdmaMeas/Implementations/Configure_/Prach.py
RsCmwWcdmaMeas/Implementations/Configure_/RfSettings.py
RsCmwWcdmaMeas/Implementations/Configure_/Tpc.py
RsCmwWcdmaMeas/Implementations/Configure_/UeChannels.py
RsCmwWcdmaMeas/Implementations/Configure_/UeSignal.py
RsCmwWcdmaMeas/Implementations/Configure_/__init__.py
RsCmwWcdmaMeas/Implementations/Configure_/Carrier_/Band.py
RsCmwWcdmaMeas/Implementations/Configure_/Carrier_/__init__.py
RsCmwWcdmaMeas/Implementations/Configure_/Cell_/Carrier.py
RsCmwWcdmaMeas/Implementations/Configure_/Cell_/__init__.py
RsCmwWcdmaMeas/Implementations/Configure_/Cell_/Carrier_/Scode.py
RsCmwWcdmaMeas/Implementations/Configure_/Cell_/Carrier_/__init__.py
RsCmwWcdmaMeas/Implementations/Configure_/MultiEval_/Amode.py
RsCmwWcdmaMeas/Implementations/Configure_/MultiEval_/CdThreshold.py
RsCmwWcdmaMeas/Implementations/Configure_/MultiEval_/Dmode.py
RsCmwWcdmaMeas/Implementations/Configure_/MultiEval_/DsFactor.py
RsCmwWcdmaMeas/Implementations/Configure_/MultiEval_/Limit.py
RsCmwWcdmaMeas/Implementations/Configure_/MultiEval_/ListPy.py
RsCmwWcdmaMeas-3.8.10.4.dist-info/METADATA
RsCmwWcdmaMeas-3.8.10.4.dist-info/WHEEL
RsCmwWcdmaMeas-3.8.10.4.dist-info/top_level.txt
RsCmwWcdmaMeas-3.8.10.4.dist-info/RECORD
